{
  "commitsAhead": 0,
  "currentCommit": "186fbebc8a4e9131b09665809a426c021eb5f13b",
  "gitRelation": "same",
  "ignoredFreshnessPaths": [
    ".ctxhelm/e2e/",
    ".planning/"
  ],
  "privacyStatus": {
    "localOnly": true,
    "remoteEmbeddingsUsed": false,
    "remoteRerankingUsed": false,
    "sourceTextLogged": false
  },
  "productCommitsAhead": 0,
  "productStatus": "current",
  "proofOnlyCommitsAhead": 0,
  "publishedAt": "2026-06-01T09:19:23Z",
  "releaseTargetCommit": "186fbebc8a4e9131b09665809a426c021eb5f13b",
  "releaseUrl": "https://github.com/thromel/ctxhelm/releases/tag/v1.1.4",
  "repo": "thromel/ctxhelm",
  "schemaVersion": 1,
  "sourceFree": true,
  "status": "current",
  "tag": "v1.1.4",
  "unsupportedActions": [
    "publishing",
    "tag creation",
    "asset upload",
    "global install",
    "global agent config mutation"
  ]
}
